hermes/__init__.py
hermes/report.py
hermes/server.py
hermes/templates/__init__.py
hermes/templates/drill.pt
hermes/templates/report.pt
hermes/templates/x
hermes/views.py
hermes_pyramid-0.0.1.dist-info/entry_points.txt
hermes_pyramid-0.0.1.dist-info/LICENSE
hermes_pyramid-0.0.1.dist-info/WHEEL
hermes_pyramid-0.0.1.dist-info/METADATA
hermes_pyramid-0.0.1.dist-info/RECORD
